LICENSE
README.md
pyproject.toml
src/flitter_pygments/__init__.py
src/flitter_pygments.egg-info/PKG-INFO
src/flitter_pygments.egg-info/SOURCES.txt
src/flitter_pygments.egg-info/dependency_links.txt
src/flitter_pygments.egg-info/entry_points.txt
src/flitter_pygments.egg-info/requires.txt
src/flitter_pygments.egg-info/top_level.txt