Metadata-Version: 2.4
Name: flitter-pygments
Version: 1.0.0b28
Summary: A Pygments plugin providing a lexer for the Flitter visuals functional programming language
Author-email: Jonathan Hogg <me@jonathanhogg.com>
Maintainer-email: Jonathan Hogg <me@jonathanhogg.com>
License: Copyright (c) 2024, Jonathan Hogg
Project-URL: Documentation, https://flitter.readthedocs.io/
Project-URL: Repository, https://github.com/jonathanhogg/pygments-flitter.git
Project-URL: Issues, https://github.com/jonathanhogg/pygments-flitter/issues
Keywords: language,opengl,live-coding,live-visuals
Classifier: Development Status :: 4 - Beta
Classifier: Intended Audience :: Developers
Classifier: License :: OSI Approved :: BSD License
Classifier: Programming Language :: Python :: 3
Classifier: Programming Language :: Python :: 3.10
Classifier: Programming Language :: Python :: 3.11
Classifier: Programming Language :: Python :: 3.12
Classifier: Programming Language :: Python :: 3.13
Classifier: Programming Language :: Python :: 3.14
Classifier: Environment :: Console
Classifier: Environment :: GPU
Classifier: Environment :: MacOS X
Classifier: Environment :: X11 Applications
Classifier: Topic :: Artistic Software
Classifier: Topic :: Multimedia :: Graphics
Classifier: Topic :: Multimedia :: Graphics :: 3D Rendering
Requires-Python: >=3.10
License-File: LICENSE
Requires-Dist: Pygments
Dynamic: license-file
